[
  {
    "@base": "iri://CAMS/",
    "@schema": "iri://CAMS#",
    "@type": "@context"
  },
  {
    "@abstract": [],
    "@id": "Event",
    "@subdocument": [],
    "@type": "Class",
    "date": "xsd:dateTime"
  },
  {
    "@documentation": {
      "@comment": "Historical hazard",
      "@properties": {
        "comment": "A comment relating to an historic hazard incident.",
        "date": "The date at which the incident occurred."
      }
    },
    "@id": "HazardEvent",
    "@inherits": "Event",
    "@key": {
      "@fields": [
        "hazard",
        "date"
      ],
      "@type": "Lexical"
    },
    "@subdocument": [],
    "@type": "Class",
    "comment": "xsd:string",
    "hazard": "Hazard"
  },
  {
    "@id": "Asset",
    "@key": {
      "@fields": [
        "asset_identifier"
      ],
      "@type": "Lexical"
    },
    "@type": "Class",
    "asset_history": {
      "@class": "Hazard",
      "@type": "Optional"
    },
    "asset_identifier": "xsd:string",
    "commisioning_date": "xsd:dateTime",
    "design_standards": "xsd:string",
    "last_maintained": "xsd:dateTime",
    "last_modified": "xsd:dateTime",
    "location": "Location",
    "name": "xsd:string"
  },
  {
    "@id": "Location",
    "@key": {
      "@type": "Random"
    },
    "@subdocument": [],
    "@type": "Class",
    "city": "xsd:string",
    "geometry_location": {
      "@class": "Geometry",
      "@type": "Optional"
    },
    "postal_code": {
      "@class": "xsd:string",
      "@type": "Optional"
    },
    "state": "xsd:string",
    "street": "xsd:string"
  },
  {
    "@id": "Point",
    "@inherits": "Geometry",
    "@key": {
      "@type": "Random"
    },
    "@subdocument": [],
    "@type": "Class",
    "coordinates": {
      "@class": "xsd:decimal",
      "@dimensions": 1,
      "@type": "Array"
    },
    "type": "Point_Type"
  },
  {
    "@id": "Hazard",
    "@type": "Enum",
    "@value": [
      "Volcanos (incl. lahars, pyroclastic flows, volcanic activity)",
      "Landslides (incl. post wildfire landslides) and Avalanches",
      "Hurricanes, Typhoons, or Cyclones",
      "Tropical/Extra Tropical of other extreme storms",
      "Coast Storm Surge",
      "Pluvial and Fluvial Flooding",
      "\"Sunny Day\" Tidal Flooding",
      "Tornadoes, Derechos, Micro-Bursts",
      "Lightning Strikes",
      "Wildfires",
      "Drought",
      "Geologic Sink Holes",
      "Pest Infestations",
      "Famine",
      "High Temperature Event",
      "Low Temperature Event",
      "Cyber Attack or Failure",
      "Other Terrorism",
      "Industrial Accident (Emissions, Releases, Spills, Ect.)"
    ]
  },
  {
    "@id": "Point_Type",
    "@type": "Enum",
    "@value": [
      "Point"
    ]
  },
  {
    "@abstract": [],
    "@id": "Geometry",
    "@key": {
      "@type": "Random"
    },
    "@subdocument": [],
    "@type": "Class"
  },
  {
    "@documentation": {
      "@comment": "Update history",
      "@properties": {
        "comment": "A comment relating to an historic hazard incident.",
        "date": "The date at which the update occurred."
      }
    },
    "@id": "UpdateEvent",
    "@inherits": "Event",
    "@key": {
      "@fields": [
        "comment",
        "date"
      ],
      "@type": "Lexical"
    },
    "@subdocument": [],
    "@type": "Class",
    "comment": "xsd:string"
  }
]